instagram_api_wrapper/__init__.py
instagram_api_wrapper/client.py
instagram_api_wrapper/exceptions.py
instagram_api_wrapper-1.0.1.dist-info/METADATA
instagram_api_wrapper-1.0.1.dist-info/RECORD
instagram_api_wrapper-1.0.1.dist-info/WHEEL
instagram_api_wrapper-1.0.1.dist-info/top_level.txt
