Metadata-Version: 2.1
Name: instagram-api-wrapper
Version: 1.0.1
Summary: Instagram api wrapper
Home-page: https://github.com/YevgeniiKaidashov/instagram_api_wrapper
Author: Yevgenii Kaidashov
Author-email: zhenya.kaidashov@gmail.com
License: UNKNOWN
Platform: UNKNOWN
Classifier: Programming Language :: Python :: 3
Classifier: Topic :: Utilities
Requires-Dist: requests
